{
  "Nodes": [
    {
      "Name": "GPUMaxFreq",
      "Path": "/sys/class/kgsl/kgsl-3d0/devfreq/max_freq",
      "Values": [
        "370000000",
        "465000000",
        "588000000",
        "647000000"
      ],
      "ResetOnInit": true
    },
    {
      "Name": "GPUMinFreq",
      "Path": "/sys/class/kgsl/kgsl-3d0/devfreq/min_freq",
      "Values": [
        "465000000",
        "370000000",
        "266000000",
        "160000000"
      ],
      "ResetOnInit": true
    },
    {
      "Name": "GPUForceRailOn",
      "Path": "/sys/class/kgsl/kgsl-3d0/force_rail_on",
      "Values": [
        "1",
        "0"
      ],
      "ResetOnInit": true
    },
    {
      "Name": "GPUForceClkOn",
      "Path": "/sys/class/kgsl/kgsl-3d0/force_clk_on",
      "Values": [
        "1",
        "0"
      ],
      "ResetOnInit": true
    },
    {
      "Name": "GPUIdleTimer",
      "Path": "/sys/class/kgsl/kgsl-3d0/idle_timer",
      "Values": [
        "10000",
        "67"
      ],
      "ResetOnInit": true
    },
    {
      "Name": "CPUBWHystTriggerCount",
      "Path": "/sys/devices/soc/soc:qcom,cpubw/devfreq/soc:qcom,cpubw/bw_hwmon/hyst_trigger_count",
      "Values": [
        "0",
        "3"
      ]
    },
    {
      "Name": "CPUBWHistMemory",
      "Path": "/sys/devices/soc/soc:qcom,cpubw/devfreq/soc:qcom,cpubw/bw_hwmon/hist_memory",
      "Values": [
        "0",
        "20"
      ]
    },
    {
      "Name": "CPUBWHystLength",
      "Path": "/sys/devices/soc/soc:qcom,cpubw/devfreq/soc:qcom,cpubw/bw_hwmon/hyst_length",
      "Values": [
        "0",
        "10"
      ]
    },
    {
      "Name": "CPUBWMinFreq",
      "Path": "/sys/devices/soc/soc:qcom,cpubw/devfreq/soc:qcom,cpubw/min_freq",
      "Values": [
        "3143",
        "1525",
        "762"
      ],
      "ResetOnInit": true
    },
    {
      "Name": "PMQoSCpuDmaLatency",
      "Path": "/dev/cpu_dma_latency",
      "Values": [
        "44",
        "100"
      ],
      "HoldFd": true
    }
  ],
  "Actions": [
    {
      "PowerHint": "INTERACTION",
      "Node": "CPUBWHystTriggerCount",
      "Duration": 0,
      "Value": "0"
    },
    {
      "PowerHint": "INTERACTION",
      "Node": "CPUBWHystLength",
      "Duration": 0,
      "Value": "0"
    },
    {
      "PowerHint": "INTERACTION",
      "Node": "CPUBWHistMemory",
      "Duration": 0,
      "Value": "0"
    },
    {
      "PowerHint": "LAUNCH",
      "Node": "GPUForceClkOn",
      "Duration": 5000,
      "Value": "1"
    },
    {
      "PowerHint": "LAUNCH",
      "Node": "GPUForceRailOn",
      "Duration": 5000,
      "Value": "1"
    },
    {
      "PowerHint": "LAUNCH",
      "Node": "GPUIdleTimer",
      "Duration": 5000,
      "Value": "10000"
    },
    {
      "PowerHint": "LAUNCH",
      "Node": "PMQoSCpuDmaLatency",
      "Duration": 2000,
      "Value": "44"
    },
    {
      "PowerHint": "LAUNCH",
      "Node": "CPUBWHystTriggerCount",
      "Duration": 2000,
      "Value": "0"
    },
    {
      "PowerHint": "LAUNCH",
      "Node": "CPUBWHystLength",
      "Duration": 2000,
      "Value": "0"
    },
    {
      "PowerHint": "LAUNCH",
      "Node": "CPUBWHistMemory",
      "Duration": 2000,
      "Value": "0"
    },
    {
      "PowerHint": "CAMERA_STREAMING",
      "Node": "PMQoSCpuDmaLatency",
      "Duration": 1000,
      "Value": "44"
    },
    {
      "PowerHint": "CAMERA_SHOT",
      "Node": "PMQoSCpuDmaLatency",
      "Duration": 1000,
      "Value": "44"
    },
    {
      "PowerHint": "CAMERA_SHOT",
      "Node": "CPUBWHystTriggerCount",
      "Duration": 1000,
      "Value": "0"
    },
    {
      "PowerHint": "CAMERA_SHOT",
      "Node": "CPUBWHystLength",
      "Duration": 1000,
      "Value": "0"
    },
    {
      "PowerHint": "CAMERA_SHOT",
      "Node": "CPUBWHistMemory",
      "Duration": 1000,
      "Value": "0"
    },
    {
      "PowerHint": "CAMERA_LAUNCH",
      "Node": "PMQoSCpuDmaLatency",
      "Duration": 1000,
      "Value": "44"
    },
    {
      "PowerHint": "EXPENSIVE_RENDERING",
      "Node": "GPUMinFreq",
      "Duration": 0,
      "Value": "465000000"
    },
    {
      "PowerHint": "EXPENSIVE_RENDERING",
      "Node": "GPUMaxFreq",
      "Duration": 0,
      "Value": "647000000"
    }
  ]
}
